README.rst
setup.py
SelectMenu.egg-info/PKG-INFO
SelectMenu.egg-info/SOURCES.txt
SelectMenu.egg-info/dependency_links.txt
SelectMenu.egg-info/requires.txt
SelectMenu.egg-info/top_level.txt
selectmenu/__init__.py
selectmenu/control.py
selectmenu/core.py
selectmenu/keybinding.py