Metadata-Version: 1.1
Name: SelectMenu
Version: 1.0.0b2
Summary: SelectMenu is the input form to choose from menu by arrow keys.
Home-page: UNKNOWN
Author: Hayato Tominaga
Author-email: takemehighermore@gmail.com
License: MIT License
Platform: UNKNOWN
Classifier: Development Status :: 4 - Beta
Classifier: Programming Language :: Python :: 2.7
Classifier: Programming Language :: Python :: 2 :: Only
Classifier: License :: OSI Approved :: MIT License
Classifier: Topic :: Terminals
Classifier: Topic :: Utilities
